gspatial_plot/__init__.py
gspatial_plot/config.py
gspatial_plot/plot.py
gspatial_plot/datasets/ne_50m_admin_0_countries.cpg
gspatial_plot/datasets/ne_50m_admin_0_countries.dbf
gspatial_plot/datasets/ne_50m_admin_0_countries.prj
gspatial_plot/datasets/ne_50m_admin_0_countries.shp
gspatial_plot/datasets/ne_50m_admin_0_countries.shx
gspatial_plot/datasets/ne_50m_geographic_lines.cpg
gspatial_plot/datasets/ne_50m_geographic_lines.dbf
gspatial_plot/datasets/ne_50m_geographic_lines.prj
gspatial_plot/datasets/ne_50m_geographic_lines.shp
gspatial_plot/datasets/ne_50m_geographic_lines.shx
gspatial_plot/datasets/ne_50m_lakes.cpg
gspatial_plot/datasets/ne_50m_lakes.dbf
gspatial_plot/datasets/ne_50m_lakes.prj
gspatial_plot/datasets/ne_50m_lakes.shp
gspatial_plot/datasets/ne_50m_lakes.shx
gspatial_plot/datasets/ne_50m_ocean.cpg
gspatial_plot/datasets/ne_50m_ocean.dbf
gspatial_plot/datasets/ne_50m_ocean.prj
gspatial_plot/datasets/ne_50m_ocean.shp
gspatial_plot/datasets/ne_50m_ocean.shx
gspatial_plot/datasets/ne_50m_rivers_lake_centerlines.cpg
gspatial_plot/datasets/ne_50m_rivers_lake_centerlines.dbf
gspatial_plot/datasets/ne_50m_rivers_lake_centerlines.prj
gspatial_plot/datasets/ne_50m_rivers_lake_centerlines.shp
gspatial_plot/datasets/ne_50m_rivers_lake_centerlines.shx
gspatial_plot/datasets/us_states.geojson
gspatial_plot-0.2.0.dist-info/LICENSE
gspatial_plot-0.2.0.dist-info/METADATA
gspatial_plot-0.2.0.dist-info/WHEEL
gspatial_plot-0.2.0.dist-info/top_level.txt
gspatial_plot-0.2.0.dist-info/RECORD
