Metadata-Version: 2.1
Name: gspatial-plot
Version: 0.2.0
Summary: A geospatial plotting library built on top of geopandas.
Home-page: https://github.com/ambeelabs/gspatial_plot/
Author: Ambee
License: MIT
Keywords: geospatial plot geopandas maps plotting graph folium
Classifier: Development Status :: 4 - Beta
Classifier: Intended Audience :: Developers
Classifier: License :: OSI Approved :: MIT License
Classifier: Programming Language :: Python :: 3.10
License-File: LICENSE
Requires-Dist: Fiona (>=1.8.22)
Requires-Dist: folium (>=0.12.1.post1)
Requires-Dist: geopandas (>=0.11.0)
Requires-Dist: mapclassify (>=2.5.0)
Requires-Dist: matplotlib (>=3.6.2)
Requires-Dist: pandas (>=1.5.2)
Requires-Dist: pyproj (>=3.4.1)
Requires-Dist: rasterio (>=1.3.8)
Requires-Dist: rioxarray (>=0.13.3)
Requires-Dist: scikit-learn (>=1.0.1)
Requires-Dist: scipy (>=1.10.0)
Requires-Dist: seaborn (>=0.12.2)
Requires-Dist: Shapely (>=1.8.2)
